<?xml version='1.0' encoding='UTF-8'?>
<pyvcp>
	<vbox>
		<relief>RIDGE</relief>         
		<bd>6</bd>
		<labelframe text="Tool Changer"> 
			<font>("Helvetica",11)</font>
			<bd>3</bd>
			<vbox>
				<hbox>
					<label><text>"Auto Mode"</text></label>
					<checkbutton><halpin>"auto-mode"</halpin></checkbutton>
					<label><text>"Machine On:"</text></label>
					<checkbutton><halpin>"machine-on"</halpin></checkbutton>
				</hbox>
				<hbox>
					<label><text>"New Tool No. (0 for no tool):"</text></label>
					<spinbox> <halpin>"new-tool-no"</halpin> <min_>0</min_> <max_>24</max_> <resolution>1</resolution> <format>"2f"</format> <font>('Arial',15)</font> </spinbox>
				</hbox>
				<button><halpin>"change-tool-btn"</halpin><text>"Change Tool"</text></button>
				<hbox>
					<label><text>"Current Tool No:"</text></label>
					<s32><width>8</width><halpin>"cur-toolno-disp"</halpin></s32>
				</hbox>
				<hbox>
					<label><text>"State:"</text></label>
					<s32><width>8</width><halpin>"changer-state-disp"</halpin></s32>
				</hbox>
				<hbox>
					<vbox>	
						<hbox>
							<label><text>"Change Request"</text></label>
							<led><off_color>"black"</off_color><size>15</size><halpin>"request-led"</halpin></led>
						</hbox>
						<hbox>
							<label><text>"Changer is Homed"</text></label>
							<led><off_color>"black"</off_color><size>15</size><halpin>"homed-led"</halpin></led>
						</hbox>
						<hbox>
							<label><text>"Change Complete"</text></label>
							<led><off_color>"black"</off_color><size>15</size><halpin>"complete-led"</halpin></led>
						</hbox>
						<hbox>
							<label><text>"Auto Mode"</text></label>
							<led><off_color>"black"</off_color><size>15</size><halpin>"auto-mode-led"</halpin></led>
						</hbox>
						<hbox>
							<label><text>"QD Reset Output"</text></label>
							<led><off_color>"black"</off_color><size>15</size><halpin>"reset-led"</halpin></led>
						</hbox>
						<hbox>
							<label><text>"QD Claw Open"</text></label>
							<led><off_color>"black"</off_color><size>15</size><halpin>"claw-open-led"</halpin></led>
						</hbox>
					</vbox>
					<vbox>
						<hbox>
							<label><text>"QD Ready"</text></label>
							<led><off_color>"black"</off_color><size>15</size><halpin>"qd-ready-led"</halpin></led>
						</hbox>
						<hbox>
							<label><text>"Tool-In"</text></label>
							<led><off_color>"black"</off_color><size>15</size><halpin>"tool-in-led"</halpin></led>
						</hbox>
						<hbox>
							<label><text>"Tool-Out"</text></label>
							<led><off_color>"black"</off_color><size>15</size><halpin>"tool-out-led"</halpin></led>
						</hbox>
						<hbox>
							<label><text>"Carousel-Home"</text></label>
							<led><off_color>"black"</off_color><size>15</size><halpin>"car-home-led"</halpin></led>
						</hbox>
						<hbox>
							<label><text>"Carousel-CW"</text></label>
							<led><off_color>"black"</off_color><size>15</size><halpin>"car-cw-led"</halpin></led>
						</hbox>
						<hbox>
							<label><text>"Carousel-CCW"</text></label>
							<led><off_color>"black"</off_color><size>15</size><halpin>"car-ccw-led"</halpin></led>
						</hbox>
						<hbox>
							<label><text>"Error"</text></label>
							<led><off_color>"black"</off_color><size>15</size><halpin>"error-led"</halpin></led>
						</hbox>
					</vbox>
				</hbox>
			</vbox>
		</labelframe>
		<labelframe text="Tool Changer Simulator"> 
			<font>("Helvetica",11)</font>
			<bd>3</bd>
			<vbox>
				<hbox>
					<label><text>"Current Pocket No:"</text></label>
					<s32><width>8</width><halpin>"cur-pocket-disp"</halpin></s32>
				</hbox>
				<hbox>
					<label><text>"Current qdsim State:"</text></label>
					<s32><width>8</width><halpin>"qdsim-state"</halpin></s32>
				</hbox>
				<hbox>
					<label><text>"Arm at Spindle"</text></label>
					<led><off_color>"black"</off_color><size>15</size><halpin>"arm-spindle"</halpin></led>
				</hbox>
			</vbox>
		</labelframe>
	</vbox>
</pyvcp>
